[
  {
    "userid": "1",
    "username": "panda",
    "image": "https://react-router-profile-images.s3.eu-north-1.amazonaws.com/p_profile.PNG",
    "webstatus": true
  },

  {
    "userid": "2",
    "username": "tellme",
    "image": "https://react-router-profile-images.s3.eu-north-1.amazonaws.com/f_profile.PNG",
    "webstatus": true
  },

  {
    "userid": "3",
    "username": "kaxina",
    "image": "https://react-router-profile-images.s3.eu-north-1.amazonaws.com/f_profile.PNG",
    "webstatus": true
  },

  {
    "userid": "4",
    "username": "calimon",
    "image": "https://react-router-profile-images.s3.eu-north-1.amazonaws.com/m_profile.PNG",
    "webstatus": false
  },

  {
    "userid": "5",
    "username": "bosty",
    "image": "https://react-router-profile-images.s3.eu-north-1.amazonaws.com/u_profile.PNG",
    "webstatus": true
  },

  {
    "userid": "6",
    "username": "drac",
    "image": "https://react-router-profile-images.s3.eu-north-1.amazonaws.com/m_profile.PNG",
    "webstatus": false
  },

  {
    "userid": "7",
    "username": "luludodo",
    "image": "https://react-router-profile-images.s3.eu-north-1.amazonaws.com/f_profile.PNG",
    "webstatus": false
  },

  {
    "userid": "8",
    "username": "sloboda",
    "image": "https://react-router-profile-images.s3.eu-north-1.amazonaws.com/m_profile.PNG",
    "webstatus": false
  },

  {
    "userid": "9",
    "username": "pan",
    "image": "https://react-router-profile-images.s3.eu-north-1.amazonaws.com/pan_profile.PNG",
    "webstatus": false
  },

  {
    "userid": "10",
    "username": "fisher",
    "image": "https://react-router-profile-images.s3.eu-north-1.amazonaws.com/m_profile.PNG",
    "webstatus": false
  }
]
